indico_cloud_captchas/__init__.py
indico_cloud_captchas/plugin.py
indico_cloud_captchas/static/dist/manifest.json
indico_cloud_captchas/static/dist/css/main.46091087.css
indico_cloud_captchas/static/dist/css/main.46091087.css.map
indico_cloud_captchas/static/dist/js/main.62bec429.bundle.js
indico_cloud_captchas/static/dist/js/main.62bec429.bundle.js.map
indico_cloud_captchas/static/dist/js/monaco.css.worker.js
indico_cloud_captchas/static/dist/js/monaco.css.worker.js.map
indico_cloud_captchas/static/dist/js/monaco.editor.worker.js
indico_cloud_captchas/static/dist/js/monaco.editor.worker.js.map
indico_cloud_captchas/static/dist/js/monaco.html.worker.js
indico_cloud_captchas/static/dist/js/monaco.html.worker.js.map
indico_cloud_captchas/translations/messages-react.pot
indico_cloud_captchas/translations/messages.pot
indico_cloud_captchas/translations/cs_CZ/LC_MESSAGES/messages-react.json
indico_cloud_captchas/translations/cs_CZ/LC_MESSAGES/messages-react.po
indico_cloud_captchas/translations/cs_CZ/LC_MESSAGES/messages.mo
indico_cloud_captchas/translations/cs_CZ/LC_MESSAGES/messages.po
indico_cloud_captchas/translations/de_DE/LC_MESSAGES/messages-react.json
indico_cloud_captchas/translations/de_DE/LC_MESSAGES/messages-react.po
indico_cloud_captchas/translations/de_DE/LC_MESSAGES/messages.mo
indico_cloud_captchas/translations/de_DE/LC_MESSAGES/messages.po
indico_cloud_captchas/translations/en_CA/LC_MESSAGES/messages-react.json
indico_cloud_captchas/translations/en_CA/LC_MESSAGES/messages-react.po
indico_cloud_captchas/translations/en_CA/LC_MESSAGES/messages.mo
indico_cloud_captchas/translations/en_CA/LC_MESSAGES/messages.po
indico_cloud_captchas/translations/en_GB/LC_MESSAGES/messages-react.json
indico_cloud_captchas/translations/en_GB/LC_MESSAGES/messages-react.po
indico_cloud_captchas/translations/en_GB/LC_MESSAGES/messages.mo
indico_cloud_captchas/translations/en_GB/LC_MESSAGES/messages.po
indico_cloud_captchas/translations/es_ES/LC_MESSAGES/messages-react.json
indico_plugin_cloud_captchas-3.3.2.dist-info/METADATA
indico_plugin_cloud_captchas-3.3.2.dist-info/WHEEL
indico_plugin_cloud_captchas-3.3.2.dist-info/entry_points.txt
indico_plugin_cloud_captchas-3.3.2.dist-info/RECORD
